lexitheras/__init__.py
lexitheras/cli.py
lexitheras/deck.py
lexitheras/scraper.py
lexitheras/search.py
lexitheras-1.0.1.dist-info/licenses/LICENSE
lexitheras-1.0.1.dist-info/METADATA
lexitheras-1.0.1.dist-info/WHEEL
lexitheras-1.0.1.dist-info/entry_points.txt
lexitheras-1.0.1.dist-info/top_level.txt
lexitheras-1.0.1.dist-info/RECORD
