Metadata-Version: 2.4
Name: lexitheras
Version: 1.0.1
Summary: Convert Perseus Greek vocabulary lists into Anki flashcard decks
Home-page: https://github.com/conorreid/lexitheras
Author: Conor Reid
Author-email: 
License-Expression: GPL-3.0
Project-URL: Homepage, https://github.com/conorreid/lexitheras
Project-URL: Repository, https://github.com/conorreid/lexitheras
Project-URL: Issues, https://github.com/conorreid/lexitheras/issues
Keywords: greek,ancient-greek,anki,flashcards,perseus,vocabulary,language-learning
Classifier: Development Status :: 5 - Production/Stable
Classifier: Intended Audience :: Education
Classifier: Topic :: Education
Classifier: Programming Language :: Python :: 3
Classifier: Programming Language :: Python :: 3.6
Classifier: Programming Language :: Python :: 3.7
Classifier: Programming Language :: Python :: 3.8
Classifier: Programming Language :: Python :: 3.9
Classifier: Programming Language :: Python :: 3.10
Classifier: Programming Language :: Python :: 3.11
Requires-Python: >=3.6
License-File: LICENSE
Requires-Dist: beautifulsoup4>=4.12.0
Requires-Dist: requests>=2.32.0
Requires-Dist: genanki>=0.13.0
Requires-Dist: lxml>=5.3.0
Requires-Dist: click>=8.1.0
Dynamic: home-page
Dynamic: license-file
Dynamic: requires-python
